{"appleSKU":"","appleTeamID":"","enableCodelessAutoInitialization":true,"products":[{"id":"com.ilink.snake.lifex10","type":0,"storeIDs":[{"store":"AppleAppStore","id":"com.ilink.snakevsblocks.apple"}],"defaultDescription":{"googleLocale":4,"title":"Life","description":"Buy life x10"},"screenshotPath":"","applePriceTier":0,"googlePrice":{"data":[49,0,0,131072],"num":0.49},"pricingTemplateID":"","descriptions":[],"udpPrice":{"data":[0,0,0,0],"num":0.0},"payouts":[]},{"id":"com.ilink.snake.noads","type":1,"storeIDs":[{"store":"AppleAppStore","id":"com.ilink.snakevsblocks.noads.apple"}],"defaultDescription":{"googleLocale":4,"title":"No Ads","description":"Remove all Ads"},"screenshotPath":"","applePriceTier":0,"googlePrice":{"data":[149,0,0,131072],"num":1.49},"pricingTemplateID":"","descriptions":[],"udpPrice":{"data":[0,0,0,0],"num":0.0},"payouts":[]}]}